rest_framework_social_auth/__init__.py
rest_framework_social_auth/adapter.py
rest_framework_social_auth/google.py
rest_framework_social_auth/serializers.py
rest_framework_social_auth/views.py
drf_social_auth-0.1.0.dist-info/LICENSE
drf_social_auth-0.1.0.dist-info/METADATA
drf_social_auth-0.1.0.dist-info/WHEEL
drf_social_auth-0.1.0.dist-info/top_level.txt
drf_social_auth-0.1.0.dist-info/RECORD
