Metadata-Version: 2.1
Name: drf-social-auth
Version: 0.1.0
Summary: DRF_social_auth is an ultra-lightweight solution for social authentication support in Django REST Framework.
Home-page: https://github.com/coaxsoft/drf-social-auth
Author: Vitalii Bazhenov
Author-email: vitalii.bazhenov@coaxsoft.com
License: ISC
Project-URL: Source, https://github.com/coaxsoft/drf-social-auth
Keywords: django rest_framework drf social auth
Platform: UNKNOWN
Classifier: Development Status :: 3 - Alpha
Classifier: Environment :: Web Environment
Classifier: Framework :: Django
Classifier: Intended Audience :: Developers
Classifier: License :: OSI Approved :: ISC License (ISCL)
Classifier: Operating System :: OS Independent
Classifier: Natural Language :: English
Classifier: Programming Language :: Python
Classifier: Programming Language :: Python :: 3
Classifier: Programming Language :: Python :: 3.6
Classifier: Programming Language :: Python :: 3.7
Classifier: Programming Language :: Python :: 3.8
Classifier: Programming Language :: Python :: 3.9
Classifier: Programming Language :: Python :: 3 :: Only
Classifier: Topic :: Internet :: WWW/HTTP
Requires-Python: >=3.6
